[
{
      "quizID":0,
      "quizFragen":[
         {
            "frage":"Wen bezeichnet man beim Fußball auch als Goalie ?",
            "antworten":[
               {
                  "text":"Mittelstürmer",
                  "check":false
               },
               {
                  "text":"Platzwart",
                  "check":false
               },
               {
                  "text":"Torwart",
                  "check":true
               },
               {
                  "text":"Schiedsrichter",
                  "check":false
               }
            ]
         },
         {
            "frage":"Warum ist Grönland kein Mitglied der FIFA ?",
            "antworten":[
               {
                  "text":"Weil es zu wenige Spieler hat",
                  "check":false
               },
               {
                  "text":"Weil es keinen Rasenplatz hat",
                  "check":true
               },
               {
                  "text":"Weil es ein Teil von Dänemark ist",
                  "check":false
               },
               {
                  "text":"Weil es keinen internationalen Flugplatz hat",
                  "check":false
               }
            ]
         },
         {
            "frage":"Welchen Preis vergibt die Sportschau regelmäßig?",
            "antworten":[
               {
                  "text":"Tor des Monats",
                  "check":true
               },
               {
                  "text":"Tor der Stunde",
                  "check":false
               },
               {
                  "text":"Tor des Spieltags",
                  "check":false
               },
               {
                  "text":"Tor des Tages",
                  "check":false
               }
            ]
         },
         {
            "frage":"Welche Mannschaft wurde 1978 im eigenen Land Fußball-Weltmeister ?",
            "antworten":[
               {
                  "text":"Uruguay",
                  "check":false
               },
               {
                  "text":"Brasilien",
                  "check":false
               },
               {
                  "text":"Kolumbien",
                  "check":false
               },
               {
                  "text":"Argentinien",
                  "check":true
               }
            ]
         },
         {
            "frage":"In welchen Stadion fand das sogenannte Jahrhundertspiel statt ?",
            "antworten":[
               {
                  "text":"Aztekenstadion, Mexiko",
                  "check":false
               },
               {
                  "text":"Wembley Stadion, London",
                  "check":false
               },
               {
                  "text":"San Siro, Mailand",
                  "check":false
               },
               {
                  "text":"Bernabeustadion, Madrid",
                  "check":true
               }
            ]
         },
         {
            "frage":"Wie lange geht eine Halbzeitpause ?",
            "antworten":[
               {
                  "text":"90 Minuten",
                  "check":false
               },
               {
                  "text":"15 Minuten",
                  "check":false
               },
               {
                  "text":"45 Minuten",
                  "check":true
               },
               {
                  "text":"30 Minuten",
                  "check":false
               }
            ]
         },
         {
            "frage":"Wie viele Spieler befinden sich auf dem Feld ?",
            "antworten":[
               {
                  "text":"10",
                  "check":false
               },
               {
                  "text":"15",
                  "check":false
               },
               {
                  "text":"22",
                  "check":true
               },
               {
                  "text":"20",
                  "check":false
               }
            ]
         },
         {
            "frage":"Wie hoch und wie breit muss ein Tor laut den Spielregeln der FIFA sein ?",
            "antworten":[
               {
                  "text":"7,32 m breit | 2,54 m hoch",
                  "check":false
               },
               {
                  "text":"7,42 m breit | 2,54 m hoch",
                  "check":false
               },
               {
                  "text":"7,42 m breit | 2,44 m hoch",
                  "check":false
               },
               {
                  "text":"7,32 m breit | 2,44 m hoch",
                  "check":true
               }
            ]
         },
         {
            "frage":"Bei welcher Situation ist ein Pfiff des Schiedsrichters nicht notwendig ?",
            "antworten":[
               {
                  "text":"Zur Wiederaufnahme des Spiels nach/bei einem Eckstoß",
                  "check":true
               },
               {
                  "text":"Zur Wiederaufnahme des Spiels nach einer Unterbrechung wegen einer Auswechslung",
                  "check":false
               },
               {
                  "text":"Zur Wiederaufnahme des Spiels nach einer Unterbrechung wegen einer Verletzung",
                  "check":false
               },
               {
                  "text":"Zur Wiederaufnahme des Spiels bei Strafstößen",
                  "check":false
               }
            ]
         },
         {
            "frage":"Welche Entscheidung trifft der Schiedsrichter, wenn ein indirekter Freistoß direkt im gegnerischen Tor einschlägt ?",
            "antworten":[
               {
                  "text":"Direkter Freistoß für den Gegner",
                  "check":false
               },
               {
                  "text":"Wiederholung",
                  "check":false
               },
               {
                  "text":"Indirekter Freistoß für den Gegner Abstoß",
                  "check":true
               },
               {
                  "text":"Abstoß",
                  "check":false
               }
            ]
         },
         {
            "frage":"Wie viel muss ein Ball laut offiziellem Regelwerk VOR dem Beginn eines Spiels MINDESTENS wiegen ?",
            "antworten":[
               {
                  "text":"390 g",
                  "check":false
               },
               {
                  "text":"430 g",
                  "check":false
               },
               {
                  "text":"410 g",
                  "check":true
               },
               {
                  "text":"450 g",
                  "check":false
               }
            ]
         },
         {
            "frage":"Welche Mannschaft gewann zum letzten Mal den Weltpokal vor dessen Abschaffung und der Einführung der FIFA Klub-Weltmeisterschaft ?",
            "antworten":[
               {
                  "text":"AC Mailand",
                  "check":false
               },
               {
                  "text":"Real Madrid",
                  "check":false
               },
               {
                  "text":"FC Porto",
                  "check":true
               },
               {
                  "text":"FC Bayern München",
                  "check":false
               }
            ]
         },
         {
            "frage":"Welche Nation musste die meisten Finalniederlagen bei einer WM-Endrunde einzustecken ? (Stand 08/2016)",
            "antworten":[
               {
                  "text":"Niederlande",
                  "check":false
               },
               {
                  "text":"Italien",
                  "check":false
               },
               {
                  "text":"Deutschland",
                  "check":true
               },
               {
                  "text":"Argentinien",
                  "check":false
               }
            ]
         },
         {
            "frage":"Wie viele Vereine aus dem gleichen Land können in der Champions League maximal an den Start gehen ?",
            "antworten":[
               {
                  "text":"4",
                  "check":false
               },
               {
                  "text":"5",
                  "check":true
               },
               {
                  "text":"7",
                  "check":false
               },
               {
                  "text":"6",
                  "check":false
               }
            ]
         },
         {
            "frage":"Der Doppelpass auf Sport1 ist eine berühmte Diskussionsrunde von Fussball-Experten. In welchem Jahr wurde die erste Sendung (damals noch auf DSF) ausgestrahlt?",
            "antworten":[
               {
                  "text":"1997",
                  "check":false
               },
               {
                  "text":"1995",
                  "check":true
               },
               {
                  "text":"1994",
                  "check":false
               },
               {
                  "text":"1996",
                  "check":false
               }
            ]
         },
         {
            "frage":"Welches dieser Stadien gehört NICHT zu den 10 größten Fussball-Stadien Europas ?",
            "antworten":[
               {
                  "text":"Estádio da Luz | Lissabon",
                  "check":true
               },
               {
                  "text":"Stadio San Paolo | Neapel",
                  "check":false
               },
               {
                  "text":"Olympiastadion Luschniki | Moskau",
                  "check":false
               },
               {
                  "text":"Croke Park | Dublin",
                  "check":false
               }
            ]
         },
         {
            "frage":"Welches Muster ist auf dem Fußball ?",
            "antworten":[
               {
                  "text":"Sechseck",
                  "check":true
               },
               {
                  "text":"Dreieck",
                  "check":false
               },
               {
                  "text":"Viereck",
                  "check":false
               },
               {
                  "text":"Fünfeck",
                  "check":false
               }
            ]
         },
         {
            "frage":"Wie nennt man den Spieler der ganz vorne im Angriff spielt ?",
            "antworten":[
               {
                  "text":"Abwehrspieler",
                  "check":false
               },
               {
                  "text":"Mittelfeldspieler",
                  "check":false
               },
               {
                  "text":"Torwart",
                  "check":false
               },
               {
                  "text":"Stürmer",
                  "check":true
               }
            ]
         },
         {
            "frage":"Wie nennt man die Klamotten der Spieler ?",
            "antworten":[
               {
                  "text":"Strampler",
                  "check":false
               },
               {
                  "text":"Trikot",
                  "check":true
               },
               {
                  "text":"Pulli und Jogginghose",
                  "check":false
               },
               {
                  "text":"Anzug",
                  "check":false
               }
            ]
         },
         {
            "frage":"Was ist eine Flanke ?",
            "antworten":[
               {
                  "text":"Ein anderes Wort für Anstoß",
                  "check":false
               },
               {
                  "text":"Ein anderes Wort für Schuss",
                  "check":false
               },
               {
                  "text":"Ein Eckstoß mit verfehltem Torschuss",
                  "check":false
               },
               {
                  "text":"Ein Eckstoß mit Torschuss in Folge",
                  "check":true
               }
            ]
         },
         {
            "frage":"Wie nennt man den Raum wo der Torwart drinnen sein darf außer Dem Tor ?",
            "antworten":[
               {
                  "text":"Strafraum",
                  "check":true
               },
               {
                  "text":"Ballraum",
                  "check":false
               },
               {
                  "text":"Vorraum",
                  "check":false
               },
               {
                  "text":"Torraum",
                  "check":false
               }
            ]
         },
         {
            "frage":"Wie lange dauert ein normales Spiel ohne Pause ?",
            "antworten":[
               {
                  "text":"100 Minuten",
                  "check":false
               },
               {
                  "text":"90 Minuten",
                  "check":true
               },
               {
                  "text":"80 Minuten",
                  "check":false
               },
               {
                  "text":"60 Minuten",
                  "check":false
               }
            ]
         },
         {
            "frage":"Welches ist das Entstehungsland des Fußballs ?",
            "antworten":[
               {
                  "text":"Brasilien",
                  "check":false
               },
               {
                  "text":"Spanien",
                  "check":false
               },
               {
                  "text":"England",
                  "check":true
               },
               {
                  "text":"Italien",
                  "check":false
               }
            ]
         },
         {
            "frage":"Wie nennt man im Fußball den Versuch eines Spielers, ein Foul vorzutäuschen ?",
            "antworten":[
               {
                  "text":"Ente",
                  "check":false
               },
               {
                  "text":"Schwalbe",
                  "check":true
               },
               {
                  "text":"Sperling",
                  "check":false
               },
               {
                  "text":"Taube",
                  "check":false
               }
            ]
         },
         {
            "frage":"Welches Fußballteam stürzte 1993 mit dem Flugzeug bei Libreville ab ?",
            "antworten":[
               {
                  "text":"Sambia",
                  "check":true
               },
               {
                  "text":"Togo",
                  "check":false
               },
               {
                  "text":"Gabun",
                  "check":false
               },
               {
                  "text":"Republik Kongo",
                  "check":false
               }
            ]
         },
         {
            "frage":"Wo wird die Fußball-WM 2018 stattfinden ?",
            "antworten":[
               {
                  "text":"Russland",
                  "check":true
               },
               {
                  "text":"Katar",
                  "check":false
               },
               {
                  "text":"Südafrika",
                  "check":false
               },
               {
                  "text":"Brasilien",
                  "check":false
               }
            ]
         },
         {
            "frage":"Wie nennt man Fans, die während eines Fußballspiels nackt über den Platz rennen ?",
            "antworten":[
               {
                  "text":"Störer",
                  "check":false
               },
               {
                  "text":"Läufer",
                  "check":false
               },
               {
                  "text":"Flitzer",
                  "check":true
               },
               {
                  "text":"Sauser",
                  "check":false
               }
            ]
         },
         {
            "frage":"Was ist Futsal ?",
            "antworten":[
               {
                  "text":"Fußball mit Softbällen",
                  "check":false
               },
               {
                  "text":"Fußball ohne Torwart",
                  "check":false
               },
               {
                  "text":"Fußballtennis",
                  "check":false
               },
               {
                  "text":"Hallenfußball",
                  "check":true
               }
            ]
         },
         {
            "frage":"Was zeigt der 4. Offizielle bei einem Fußballspiel ab der 90. Minute an ?",
            "antworten":[
               {
                  "text":"Torschützen",
                  "check":false
               },
               {
                  "text":"Zuschauerzahl",
                  "check":false
               },
               {
                  "text":"Trikotsponsoren",
                  "check":false
               },
               {
                  "text":"Nachspielzeit",
                  "check":true
               }
            ]
         },
         {
            "frage":"Wer wurde 1999 von der FIFA zum besten Spieler des Jahres gewählt ?",
            "antworten":[
               {
                  "text":"Rivaldo",
                  "check":true
               },
               {
                  "text":"Ronaldo",
                  "check":false
               },
               {
                  "text":"Zidane",
                  "check":false
               },
               {
                  "text":"Matthäus",
                  "check":false
               }
            ]
         }
      ]
   },
{
      "quizID":1,
      "quizFragen":[
         {
            "frage":"Wer trainiert in der Saison 16/17 den Rekordmeister FC Bayern München?",
            "antworten":[
               {
                  "text":"Pep Guardiola",
                  "check":false
               },
               {
                  "text":"Jogi Löw",
                  "check":false
               },
               {
                  "text":"Carlo Ancelotti",
                  "check":true
               },
               {
                  "text":"Jürgen Klopp",
                  "check":false
               }
            ]
         },
         {
            "frage":"Welche zwei Vereine sind aufgestiegen und sind nun Bundesligisten?",
            "antworten":[
               {
                  "text":"Nürnberg und Kaiserslautern",
                  "check":false
               },
               {
                  "text":"RB Leipzig und SC Freiburg",
                  "check":true
               },
               {
                  "text":"RB Leipzig und Nürnberg",
                  "check":false
               },
               {
                  "text":"SC Freiburg und Kaiserslautern",
                  "check":false
               }
            ]
         },
         {
            "frage":"Welcher Traditionsclub stieg in der Saison 15/16 ab und spielt nun in der Saison 16/17 2. Bundesliga?",
            "antworten":[
               {
                  "text":"VfB Stuttgart",
                  "check":true
               },
               {
                  "text":"SV Werder Bremen",
                  "check":false
               },
               {
                  "text":"1. FC Köln",
                  "check":false
               },
               {
                  "text":"Hamburger SV",
                  "check":false
               }
            ]
         },
         {
            "frage":"Wer trainiert die TSG 1899 Hoffenheim in der Saison 16/17?",
            "antworten":[
               {
                  "text":"Huub Stevens",
                  "check":false
               },
               {
                  "text":"Markus Gisdol",
                  "check":false
               },
               {
                  "text":"Norbert Maier",
                  "check":false
               },
               {
                  "text":"Julian Nagelsmann ",
                  "check":true
               }
            ]
         },
         {
            "frage":"Wer ist der einzige US-amerikanische Spieler im Kader des FC Bayern München? (Saison 16/17)",
            "antworten":[
               {
                  "text":"Kingsley Coman",
                  "check":false
               },
               {
                  "text":"Niklas Dorsch",
                  "check":false
               },
               {
                  "text":"Fabian Benko",
                  "check":false
               },
               {
                  "text":"Julian Green ",
                  "check":true
               }
            ]
         },
         {
            "frage":"Welches Mittelfeld Talent wechselte erst von Borussia Dortmund zum FC Bayern und dann vom FC Bayern zu Borussia Dortmund??",
            "antworten":[
               {
                  "text":"Markus Götze",
                  "check":false
               },
               {
                  "text":"Fabian Götze",
                  "check":false
               },
               {
                  "text":"Mario Götze",
                  "check":true
               },
               {
                  "text":"Marcus Götze",
                  "check":false
               }
            ]
         },
         {
            "frage":"Wann wurde Bundesliga Neuling RB Leipzig gegründet??",
            "antworten":[
               {
                  "text":"2007",
                  "check":false
               },
               {
                  "text":"2006",
                  "check":false
               },
               {
                  "text":"2009",
                  "check":true
               },
               {
                  "text":"2008",
                  "check":false
               }
            ]
         },
         {
            "frage":"Während Darmstadt 98 eine Mitglieder-Anzahl von knapp 7400 hat, hat RB Leipzig eine Mitglieder-Anzahl von...?",
            "antworten":[
               {
                  "text":"650",
                  "check":false
               },
               {
                  "text":"5000",
                  "check":false
               },
               {
                  "text":"500",
                  "check":false
               },
               {
                  "text":"600",
                  "check":true
               }
            ]
         },
         {
            "frage":"Wie lautet der Vorname des Stürmers von BVB, Aubameyang?",
            "antworten":[
               {
                  "text":"Pierre-Emerick ",
                  "check":true
               },
               {
                  "text":"Pierre-Johnny",
                  "check":false
               },
               {
                  "text":"Pierre-Julian",
                  "check":false
               },
               {
                  "text":"Emerick-Pierre",
                  "check":false
               }
            ]
         },
         {
            "frage":"Welches große Unternehmen aus Darmstadt verzichtet freiwillig auf die Namensrechte am Stadion in Darmstadt, in Gedenken an den verstorbenen Fan Johnny Heimes?",
            "antworten":[
               {
                  "text":"Samsung",
                  "check":false
               },
               {
                  "text":"Deutsche Telekom",
                  "check":false
               },
               {
                  "text":"Merck",
                  "check":true
               },
               {
                  "text":"Fraport",
                  "check":false
               }
            ]
         },
         {
            "frage":"Wie heißt der aktuelle top Torschütze des 1.FC Kölns?",
            "antworten":[
               {
                  "text":"Robert Lewandowski",
                  "check":false
               },
               {
                  "text":"Yunus Malli",
                  "check":false
               },
               {
                  "text":"Anthony Modeste",
                  "check":true
               },
               {
                  "text":"Yussuf Poulsen",
                  "check":false
               }
            ]
         },
         {
            "frage":"Wer wurde deutscher Meister 2015/16?",
            "antworten":[
               {
                  "text":"Leverkusen",
                  "check":false
               },
               {
                  "text":"FC Bayern München",
                  "check":true
               },
               {
                  "text":"Hannover 96",
                  "check":false
               },
               {
                  "text":"Mönchengladbach",
                  "check":false
               }
            ]
         },
         {
            "frage":"Wer wurde 2.?",
            "antworten":[
               {
                  "text":"Dortmund",
                  "check":true
               },
               {
                  "text":"Wolfsburg",
                  "check":false
               },
               {
                  "text":"Gladbach",
                  "check":false
               },
               {
                  "text":"Leverkusen",
                  "check":false
               }
            ]
         },
         {
            "frage":"Wer trainiert die TSG 1899 Hoffenheim in der Saison 16/17?",
            "antworten":[
               {
                  "text":"Gladbach",
                  "check":false
               },
               {
                  "text":"Wolfsburg",
                  "check":false
               },
               {
                  "text":"Mainz",
                  "check":false
               },
               {
                  "text":"Leverkusen",
                  "check":true
               }
            ]
         },
         {
            "frage":"Wer von diesen Vereinen kam nicht auf die Plätze 1-7?",
            "antworten":[
               {
                  "text":"Mainz",
                  "check":false
               },
               {
                  "text":"Hertha Berlin",
                  "check":false
               },
               {
                  "text":"Gladbach",
                  "check":false
               },
               {
                  "text":"Wolfsburg",
                  "check":true
               }
            ]
         },
         {
            "frage":"Torschützenkönig 2015/16 wurde ?",
            "antworten":[
               {
                  "text":"Pierre-Emerick Aubameyang",
                  "check":false
               },
               {
                  "text":"Stefan Kießling",
                  "check":false
               },
               {
                  "text":"Robert Lewandowski",
                  "check":true
               },
               {
                  "text":"Sandro Wagner",
                  "check":false
               }
            ]
         },
         {
            "frage":"Welcher Trainer rettete Hoffenheim den Klassenerhalt?",
            "antworten":[
               {
                  "text":"Ralf Ranick",
                  "check":false
               },
               {
                  "text":"Markus Gisdol",
                  "check":false
               },
               {
                  "text":"Julian Nagelsmann",
                  "check":true
               },
               {
                  "text":"Huub Stevens",
                  "check":false
               }
            ]
         },
         {
            "frage":"Trainer von Bayern war diese Saison 2015/16?",
            "antworten":[
               {
                  "text":"Horst Seehofer",
                  "check":false
               },
               {
                  "text":"Thomas Tuchel",
                  "check":false
               },
               {
                  "text":"Carlo Ancelotti",
                  "check":false
               },
               {
                  "text":"Pep Guardiola",
                  "check":true
               }
            ]
         },
         {
            "frage":"Kevin Kuranyi schoss in 14 Spielen unglaubliche... Tore?",
            "antworten":[
               {
                  "text":"0",
                  "check":true
               },
               {
                  "text":"10",
                  "check":false
               },
               {
                  "text":"4",
                  "check":false
               },
               {
                  "text":"5",
                  "check":false
               }
            ]
         },
         {
            "frage":"Zweitbester Torschütze wurde?",
            "antworten":[
               {
                  "text":"Kuranyi",
                  "check":false
               },
               {
                  "text":"Lewandowski",
                  "check":false
               },
               {
                  "text":"Aubameyang",
                  "check":true
               },
               {
                  "text":"Huntelaar",
                  "check":false
               }
            ]
         },
         {
            "frage":"Die meisten Torvorlagen machte...?",
            "antworten":[
               {
                  "text":"Lewandowski",
                  "check":false
               },
               {
                  "text":"Müller",
                  "check":false
               },
               {
                  "text":"Mkhitaryan",
                  "check":true
               },
               {
                  "text":"Ribery",
                  "check":false
               }
            ]
         },
         {
            "frage":"KEINE gelb/rote Karte bekam?",
            "antworten":[
               {
                  "text":"Meier",
                  "check":false
               },
               {
                  "text":"Bagfrede",
                  "check":true
               },
               {
                  "text":"Kramaric",
                  "check":false
               },
               {
                  "text":"Medojevic",
                  "check":false
               }
            ]
         },
         {
            "frage":"Zuerst etwas zur Gründung der Bundesliga: Wann war die erste Bundesliga Saison?",
            "antworten":[
               {
                  "text":"1963/64",
                  "check":true
               },
               {
                  "text":"1949/50",
                  "check":false
               },
               {
                  "text":"1971/72",
                  "check":false
               },
               {
                  "text":"1968/69",
                  "check":false
               }
            ]
         },
         {
            "frage":"Welcher war, Stand 2016, der schlechteste Bundesligaverein aller Zeiten?",
            "antworten":[
               {
                  "text":"Karlsruher SC",
                  "check":false
               },
               {
                  "text":"Arminia Bielefeld",
                  "check":false
               },
               {
                  "text":"MSV Duisburg",
                  "check":false
               },
               {
                  "text":"Tasmania 1900 Berlin",
                  "check":true
               }
            ]
         },
         {
            "frage":"Welcher Verein stieg noch nie aus der Bundesliga ab UND war Gründungsmitglied?",
            "antworten":[
               {
                  "text":"FC Bayern München",
                  "check":false
               },
               {
                  "text":"VfB Stuttgart",
                  "check":false
               },
               {
                  "text":"SV Werder Bremen",
                  "check":false
               },
               {
                  "text":"Hamburger SV",
                  "check":true
               }
            ]
         },
         {
            "frage":"Was war der höchste Bundesligasieg aller Zeiten?",
            "antworten":[
               {
                  "text":"9:0",
                  "check":false
               },
               {
                  "text":"14:1",
                  "check":false
               },
               {
                  "text":"12:0",
                  "check":true
               },
               {
                  "text":"15:3",
                  "check":false
               }
            ]
         },
         {
            "frage":"Wie viele Vereine beinhaltete die Bundesliga bei ihrer Gründung?",
            "antworten":[
               {
                  "text":"20",
                  "check":false
               },
               {
                  "text":"18",
                  "check":false
               },
               {
                  "text":"16",
                  "check":true
               },
               {
                  "text":"12",
                  "check":false
               }
            ]
         },
         {
            "frage":"Wie lautet das Kürzel für die Bundesliga?",
            "antworten":[
               {
                  "text":"BS",
                  "check":false
               },
               {
                  "text":"BA",
                  "check":false
               },
               {
                  "text":"BD",
                  "check":false
               },
               {
                  "text":"BL",
                  "check":true
               }
            ]
         },
         {
            "frage":"Wer ist Rekordtorschütze der BL",
            "antworten":[
               {
                  "text":"Gerd Müller",
                  "check":true
               },
               {
                  "text":"Thomas Müller",
                  "check":false
               },
               {
                  "text":"Pele",
                  "check":false
               },
               {
                  "text":"Claudio Pizarro",
                  "check":false
               }
            ]
         },
         {
            "frage":"Wann begann die aktuelle Saison?",
            "antworten":[
               {
                  "text":"27. August 2016",
                  "check":false
               },
               {
                  "text":"2. September 2016",
                  "check":false
               },
               {
                  "text":"26. August 2016",
                  "check":true
               },
               {
                  "text":"22. August 2016",
                  "check":false
               }
            ]
         }
      ]
   },
   {
      "quizID":2,
      "quizFragen":[
         {
            "frage":"Wen besiegte der FC Liverpool im Champions-League Finale 2005 nach 0:4 Rückstand im Elfmeterschießen?",
            "antworten":[
               {
                  "text":"FC Barcelona",
                  "check":false
               },
               {
                  "text":"FC Bayern München",
                  "check":false
               },
               {
                  "text":" AC Mailand",
                  "check":true
               },
               {
                  "text":"Real Madrid",
                  "check":false
               }
            ]
         },
         {
            "frage":"Welche beiden MAN U Stars sorgten in der Nachspielzeit des CL-Finals 1999 gegen den FC Bayern für den 2:1 Sieg der Engländer?",
            "antworten":[
               {
                  "text":"Solskjear und Nani",
                  "check":false
               },
               {
                  "text":" Sheringham und Solskjear",
                  "check":true
               },
               {
                  "text":"Scholes und Giggs",
                  "check":false
               },
               {
                  "text":"Sheringham und Nani",
                  "check":false
               }
            ]
         },
         {
            "frage":"Welche beiden Deutschen Teams standen sich im CL-Finale 2013 gegenüber?",
            "antworten":[
               {
                  "text":"FC Bayern München und Borussia Dortmund",
                  "check":true
               },
               {
                  "text":"Borussia Dortmund und Bayer Leverkusen",
                  "check":false
               },
               {
                  "text":"Bayer Leverkusen und FC Bayern München",
                  "check":false
               },
               {
                  "text":"Schalke 04 und Borussia Dortmund",
                  "check":false
               }
            ]
         },
         {
            "frage":"Auf den wievielten Champions - League Titel wartet Real Madrid?",
            "antworten":[
               {
                  "text":"Den 11.",
                  "check":false
               },
               {
                  "text":"Den 8.",
                  "check":false
               },
               {
                  "text":"Den 9.",
                  "check":false
               },
               {
                  "text":"Den 10.",
                  "check":true
               }
            ]
         },
         {
            "frage":"Wer erzielte das schnellste CL-Tor der Geschichte?",
            "antworten":[
               {
                  "text":"Christiano Ronaldo (Real Madrid)",
                  "check":false
               },
               {
                  "text":"Filippo Inzaghi (AC Milan)",
                  "check":false
               },
               {
                  "text":"Lionel Messi (FC Barcelona)",
                  "check":false
               },
               {
                  "text":"Roy Makaay (Bayern München)",
                  "check":true
               }
            ]
         },
         {
            "frage":"Welche deutsche Mannschaft gewann als erste die Uefa Champions - League?",
            "antworten":[
               {
                  "text":"FC Bayern München",
                  "check":false
               },
               {
                  "text":"FC Schalke 04",
                  "check":false
               },
               {
                  "text":"Borussia Dortmund",
                  "check":true
               },
               {
                  "text":"Bayer Leverkusen",
                  "check":false
               }
            ]
         },
         {
            "frage":"Wer ist mit 71 Toren Rekordtorschütze der Champions - League?",
            "antworten":[
               {
                  "text":"Ryan Giggs",
                  "check":false
               },
               {
                  "text":"Ruud van Nistelrooy",
                  "check":false
               },
               {
                  "text":"Raul",
                  "check":true
               },
               {
                  "text":"Xavi",
                  "check":false
               }
            ]
         },
         {
            "frage":"Wie hieß die Champions - League früher?",
            "antworten":[
               {
                  "text":"FIFA-Cup",
                  "check":false
               },
               {
                  "text":"UEFA-Cup",
                  "check":false
               },
               {
                  "text":"Europapokal der Pokalsieger",
                  "check":false
               },
               {
                  "text":" Eurapokal der Landesmeister",
                  "check":true
               }
            ]
         },
         {
            "frage":"Welche Mannschaft konnte je den CL -Titel verteidigen?",
            "antworten":[
               {
                  "text":"Gar keine",
                  "check":true
               },
               {
                  "text":"Real Madrid",
                  "check":false
               },
               {
                  "text":"FC Bayern München",
                  "check":false
               },
               {
                  "text":"FC Barcelona",
                  "check":false
               }
            ]
         },
         {
            "frage":"Wie hieß der Torhüter des FC Valencia in der CL- Saison 00/01, als der FC Valencia im Finale dem FC Bayern München nach Elfmeterschießen unterlag?",
            "antworten":[
               {
                  "text":"Iker Casillas",
                  "check":false
               },
               {
                  "text":"Victor Valdes",
                  "check":false
               },
               {
                  "text":"Santiago Canizares",
                  "check":true
               },
               {
                  "text":"Sepp Maier",
                  "check":false
               }
            ]
         },
         {
            "frage":"Wie viele Vereine nehmen an der Champions League-Gruppenphase teil?",
            "antworten":[
               {
                  "text":"64",
                  "check":false
               },
               {
                  "text":"16",
                  "check":false
               },
               {
                  "text":"32",
                  "check":true
               },
               {
                  "text":"24",
                  "check":false
               }
            ]
         },
         {
            "frage":"Wie viele englische Teams haben sich für die Gruppenphase qualifiziert?",
            "antworten":[
               {
                  "text":"3",
                  "check":false
               },
               {
                  "text":"4",
                  "check":true
               },
               {
                  "text":"1",
                  "check":false
               },
               {
                  "text":"2",
                  "check":false
               }
            ]
         },
         {
            "frage":"Die Bayern hatten drei Gruppengegner, wer waren diese?",
            "antworten":[
               {
                  "text":" Juventus, Bordeaux und Haifa",
                  "check":true
               },
               {
                  "text":"Mainz, Frankfurt und Hoffenheim",
                  "check":false
               },
               {
                  "text":"Barcelona, Arsenal und Inter",
                  "check":false
               },
               {
                  "text":"Chelsea, Valencia und Benfica",
                  "check":false
               }
            ]
         },
         {
            "frage":"Wie viele italienische Mannschaften waren für die Gruppenphase qualifiziert?",
            "antworten":[
               {
                  "text":"1",
                  "check":false
               },
               {
                  "text":"0",
                  "check":false
               },
               {
                  "text":"2",
                  "check":false
               },
               {
                  "text":"3",
                  "check":true
               }
            ]
         },
         {
            "frage":"Im Achtelfinale spielt der VfB Stuttgart gegen wen?",
            "antworten":[
               {
                  "text":"FC Chelsea",
                  "check":false
               },
               {
                  "text":"FC Internazionale",
                  "check":false
               },
               {
                  "text":"FC Zürich",
                  "check":false
               },
               {
                  "text":"FC Barcelona",
                  "check":true
               }
            ]
         },
         {
            "frage":"Welche Mannschaft konnte kein einziges Spiel gewinnen und kein einziges Tor erzielen?",
            "antworten":[
               {
                  "text":"Fortuna Düsseldorf",
                  "check":false
               },
               {
                  "text":"Atlético Madrid",
                  "check":false
               },
               {
                  "text":"Maccabi Haifa",
                  "check":true
               },
               {
                  "text":"Apoel Nikosia",
                  "check":false
               }
            ]
         },
         {
            "frage":"Wie viele Tore erzielte Cristiano Ronaldo bei seinem Champions League-Debüt für Real Madrid?",
            "antworten":[
               {
                  "text":"Eins",
                  "check":false
               },
               {
                  "text":"Drei",
                  "check":false
               },
               {
                  "text":"Zwei",
                  "check":true
               },
               {
                  "text":"Vier",
                  "check":false
               }
            ]
         },
         {
            "frage":"Welches dieser Spiele sorgte für die Sensation der Vorrunde?",
            "antworten":[
               {
                  "text":"FC Bayern - Maccabi Haifa, welches Haifa mit 3:0 gewann",
                  "check":false
               },
               {
                  "text":"AC Mailand - FC Zürich, denn Zürich gewann völlig überraschend mit 4:1",
                  "check":false
               },
               {
                  "text":"FC Chelsea - Apoel Nikosia, welches Nikosia mit 4:2 gewann",
                  "check":false
               },
               {
                  "text":"FC Barcelona - Rubin Kasan, welches Kasan mit 2:1 gewann",
                  "check":true
               }
            ]
         },
         {
            "frage":"Welches Derby gab es in der Gruppenphase zu bestaunen?",
            "antworten":[
               {
                  "text":" Es gab kein Derby",
                  "check":true
               },
               {
                  "text":"Inter Mailand - AC Mailand",
                  "check":false
               },
               {
                  "text":"FC Arsenal - FC Chelsea",
                  "check":false
               },
               {
                  "text":"Atlético Madrid - Real Madrid",
                  "check":false
               }
            ]
         },
         {
            "frage":"In welchem Stadion wird im Mai 2010 das Finale ausgetragen?",
            "antworten":[
               {
                  "text":"Stamford Bridge",
                  "check":false
               },
               {
                  "text":"Hampden Park",
                  "check":false
               },
               {
                  "text":" Santiago Bernabéu",
                  "check":true
               },
               {
                  "text":"Camp Nou",
                  "check":false
               }
            ]
         },
         {
            "frage":"Welcher Premier-League-Manager war 1993/94 der Top-Scorer der Champions League?",
            "antworten":[
               {
                  "text":"Gianluca Vialli",
                  "check":false
               },
               {
                  "text":"Ruud Gullit",
                  "check":false
               },
               {
                  "text":"Ronald Koeman",
                  "check":true
               },
               {
                  "text":"Roberto Mancini",
                  "check":false
               }
            ]
         },
         {
            "frage":"Der damalige BVB-Youngster Ricken besiegelte Juves überraschende Niederlage mit einem grandiosen Lüpfer.",
            "antworten":[
               {
                  "text":"Andreas Möller",
                  "check":false
               },
               {
                  "text":"Lars Ricken",
                  "check":true
               },
               {
                  "text":"Hans Günther",
                  "check":false
               },
               {
                  "text":"Karl-Heinz Riedle",
                  "check":false
               }
            ]
         },
         {
            "frage":"Welcher Star der legendären Ajax-Mannschaft von 1995 spielte nicht beim AC Milan?",
            "antworten":[
               {
                  "text":"Marc Overmars",
                  "check":true
               },
               {
                  "text":"Edgar Davids",
                  "check":false
               },
               {
                  "text":"Clarence Seedorf",
                  "check":false
               },
               {
                  "text":"Michael Reiziger",
                  "check":false
               }
            ]
         },
         {
            "frage":"Wer traf im CL-Finale 1999 gegen Manchester United für Bayern?",
            "antworten":[
               {
                  "text":"Carsten Jancker",
                  "check":false
               },
               {
                  "text":"Lothar Matthäus",
                  "check":false
               },
               {
                  "text":"Stefan Effenberg",
                  "check":false
               },
               {
                  "text":"Mario Basler",
                  "check":true
               }
            ]
         },
         {
            "frage":"Welcher Real-Star erzielte den Siegtreffer im Endspiel 1998 gegen Juventus?",
            "antworten":[
               {
                  "text":"Raul",
                  "check":false
               },
               {
                  "text":"Davor Suker",
                  "check":false
               },
               {
                  "text":"Clarence Seedorf",
                  "check":false
               },
               {
                  "text":"Predrag Mijatovic",
                  "check":true
               }
            ]
         },
         {
            "frage":"Welcher Blackburn-Stürmer verbuchte 1995/96 in der Champions League einen Hattrick?",
            "antworten":[
               {
                  "text":"Chris Sutton",
                  "check":false
               },
               {
                  "text":"Alan Shearer",
                  "check":false
               },
               {
                  "text":"Mike Newell",
                  "check":true
               },
               {
                  "text":"Kevin Gallacher",
                  "check":false
               }
            ]
         },
         {
            "frage":"In welcher Champions-League-Partie fielen die meisten Tore?",
            "antworten":[
               {
                  "text":"Real-Bayern 7:3",
                  "check":false
               },
               {
                  "text":"Barca-Inter 6:2",
                  "check":false
               },
               {
                  "text":"Monaco-Deportivo 8:3",
                  "check":true
               },
               {
                  "text":"Deportivo-Milan 5:4",
                  "check":false
               }
            ]
         },
         {
            "frage":"Wann gewann Jupp Heynckes seinen ersten Titel in der Königsklasse?",
            "antworten":[
               {
                  "text":"1997 Borussia Dortmund",
                  "check":false
               },
               {
                  "text":"1993 Marseille",
                  "check":false
               },
               {
                  "text":"1988 PSV Eidhoven",
                  "check":false
               },
               {
                  "text":"1998 Real Madrid",
                  "check":true
               }
            ]
         },
         {
            "frage":"Wie oft traf Cristiano Ronaldo in elf Spielen der CL-Saison 2014/15?",
            "antworten":[
               {
                  "text":"17",
                  "check":true
               },
               {
                  "text":"11",
                  "check":false
               },
               {
                  "text":"13",
                  "check":false
               },
               {
                  "text":"15",
                  "check":false
               }
            ]
         },
         {
            "frage":"Welcher Chelsea-Spieler traf im Jahr 2000 drei Mal gegen Barcelona?",
            "antworten":[
               {
                  "text":"Gustavo Poyet",
                  "check":false
               },
               {
                  "text":"Chris Sutton",
                  "check":false
               },
               {
                  "text":"Tore Andre Flo",
                  "check":true
               },
               {
                  "text":"Gianfranco Zola",
                  "check":false
               }
            ]
         }
      ]
   },
   {
      "quizID":3,
      "quizFragen":[
         {
            "frage":"Warum spielt mal Fußball mit Ball?",
            "antworten":[
               {
                  "text":"Ist doch logo",
                  "check":false
               },
               {
                  "text":"omg was ne dumme Frage",
                  "check":false
               },
               {
                  "text":"halts maul",
                  "check":true
               },
               {
                  "text":"Weil Ball im Namen ist",
                  "check":false
               }
            ]
         },
         {
            "frage":"Wer bekommt die meisten Bälle ins Gesicht?",
            "antworten":[
               {
                  "text":"Torwart",
                  "check":false
               },
               {
                  "text":"Der Trainer",
                  "check":false
               },
               {
                  "text":"HSV",
                  "check":false
               },
               {
                  "text":"Deine du weißt schon was",
                  "check":true
               }
            ]
         },
         {
            "frage":"Warum ist der Himmel blau?",
            "antworten":[
               {
                  "text":"Weil der Ball Rund ist",
                  "check":false
               },
               {
                  "text":"1.FC Köln",
                  "check":true
               },
               {
                  "text":"Milch",
                  "check":false
               },
               {
                  "text":"Gras",
                  "check":false
               }
            ]
         },
         {
            "frage":"Warum ist Gras krass?",
            "antworten":[
               {
                  "text":"Es kennt keinen Hass",
                  "check":true
               },
               {
                  "text":"Es ist nicht blass",
                  "check":false
               },
               {
                  "text":"Es wird nass",
                  "check":false
               },
               {
                  "text":"Weil Fass",
                  "check":false
               }
            ]
         },
         {
            "frage":"Was geht ab?",
            "antworten":[
               {
                  "text":"Dönerkebab",
                  "check":false
               },
               {
                  "text":"Pap­per­la­papp",
                  "check":false
               },
               {
                  "text":"Gib mir dein Bein",
                  "check":false
               },
               {
                  "text":"Nichts",
                  "check":true
               }
            ]
         },
         {
            "frage":"Wer kennt schon alle Fußball-Fachwörter?",
            "antworten":[
               {
                  "text":"Ich",
                  "check":false
               },
               {
                  "text":"Du",
                  "check":false
               },
               {
                  "text":"Fußball",
                  "check":true
               },
               {
                  "text":"Götze",
                  "check":false
               }
            ]
         },
         {
            "frage":"Diese Fragen sind komisch?",
            "antworten":[
               {
                  "text":"Das ist keine Frage",
                  "check":false
               },
               {
                  "text":"Kann sein",
                  "check":false
               },
               {
                  "text":"Die sind Strange",
                  "check":true
               },
               {
                  "text":"Ja",
                  "check":false
               }
            ]
         },
         {
            "frage":"Fuß...",
            "antworten":[
               {
                  "text":"massage",
                  "check":false
               },
               {
                  "text":"pilz",
                  "check":false
               },
               {
                  "text":"fetisch",
                  "check":false
               },
               {
                  "text":"ball",
                  "check":true
               }
            ]
         },
         {
            "frage":"Brauchst du hilfe?",
            "antworten":[
               {
                  "text":"Ein wenig",
                  "check":true
               },
               {
                  "text":"Pepe braucht hilfe",
                  "check":false
               },
               {
                  "text":"Nö",
                  "check":false
               },
               {
                  "text":"Jein",
                  "check":false
               }
            ]
         },
         {
            "frage":"Was ist Rund und ist kein Ball?",
            "antworten":[
               {
                  "text":"Ein Ei",
                  "check":false
               },
               {
                  "text":"Nichts",
                  "check":false
               },
               {
                  "text":"Keine Ahnung",
                  "check":true
               },
               {
                  "text":"Beifall",
                  "check":false
               }
            ]
         },
         {
            "frage":"Wie wird man Fußballer?",
            "antworten":[
               {
                  "text":"Mit einem Ball",
                  "check":true
               },
               {
                  "text":"Mit Ehrgeiz",
                  "check":false
               },
               {
                  "text":"Mit Füßen statt Händen",
                  "check":false
               },
               {
                  "text":"Einfach so",
                  "check":false
               }
            ]
         },
         {
            "frage":"Wer ist der meister des Balls?",
            "antworten":[
               {
                  "text":"Der Ball selber",
                  "check":false
               },
               {
                  "text":"Der Fuß",
                  "check":true
               },
               {
                  "text":"Gott",
                  "check":false
               },
               {
                  "text":"Midi-Chlorianer",
                  "check":false
               }
            ]
         },
         {
            "frage":"Wer wurde 2.?",
            "antworten":[
               {
                  "text":"Der 2.",
                  "check":false
               },
               {
                  "text":"Der 3. von vorgestern",
                  "check":false
               },
               {
                  "text":"Jemand",
                  "check":true
               },
               {
                  "text":"Niemand",
                  "check":false
               }
            ]
         },
         {
            "frage":"Welche Frage hättest du gerne in diesem Quiz?",
            "antworten":[
               {
                  "text":"Ich hasse dein Quiz!",
                  "check":true
               },
               {
                  "text":"Du stinkst",
                  "check":false
               },
               {
                  "text":"Keine",
                  "check":false
               },
               {
                  "text":"Wer war der Trainer von Bayern diese Saison 2015/16?",
                  "check":false
               }
            ]
         },
         {
            "frage":"Was ist der beste Platz?",
            "antworten":[
               {
                  "text":"1.",
                  "check":true
               },
               {
                  "text":"5.",
                  "check":false
               },
               {
                  "text":"10.",
                  "check":false
               },
               {
                  "text":"6889.",
                  "check":false
               }
            ]
         },
         {
            "frage":"Wer ist der König?",
            "antworten":[
               {
                  "text":"Was hat das mit Fußball zu tun",
                  "check":false
               },
               {
                  "text":"Was für ein König",
                  "check":false
               },
               {
                  "text":"Julien",
                  "check":true
               },
               {
                  "text":"Kingpin",
                  "check":false
               }
            ]
         },
         {
            "frage":"Wie viele dumme Fragen kann man sich ausdenken?",
            "antworten":[
               {
                  "text":"20",
                  "check":false
               },
               {
                  "text":"10",
                  "check":false
               },
               {
                  "text":"30",
                  "check":true
               },
               {
                  "text":"40",
                  "check":false
               }
            ]
         },
         {
            "frage":"Fußball",
            "antworten":[
               {
                  "text":"Was wird getreten?",
                  "check":false
               },
               {
                  "text":"Was fliegt wie ein Ball?",
                  "check":false
               },
               {
                  "text":"Was ist ein Fußball?",
                  "check":true
               },
               {
                  "text":"Was ist Rund?",
                  "check":false
               }
            ]
         },
         {
            "frage":"Lel?",
            "antworten":[
               {
                  "text":"lul",
                  "check":true
               },
               {
                  "text":"kek",
                  "check":false
               },
               {
                  "text":"lmao",
                  "check":false
               },
               {
                  "text":"rofl",
                  "check":false
               }
            ]
         },
         {
            "frage":"Wie ist das Wetter heute?",
            "antworten":[
               {
                  "text":"Schlecht",
                  "check":false
               },
               {
                  "text":"Sehr schlecht",
                  "check":false
               },
               {
                  "text":"Ausserordentlich schlecht",
                  "check":true
               },
               {
                  "text":"geht so",
                  "check":false
               }
            ]
         },
         {
            "frage":"Hat dieses Quiz was mit Fußball zu tun?",
            "antworten":[
               {
                  "text":"nein",
                  "check":false
               },
               {
                  "text":"nicht wirklich",
                  "check":true
               },
               {
                  "text":"nur zu 1% (was nicht stimmen kann)",
                  "check":false
               },
               {
                  "text":"sehr wenig",
                  "check":false
               }
            ]
         },
         {
            "frage":"Das Fußballfeld ist wie ein ...",
            "antworten":[
               {
                  "text":"Eimer",
                  "check":false
               },
               {
                  "text":"Becher",
                  "check":false
               },
               {
                  "text":"Tonne",
                  "check":false
               },
               {
                  "text":"Teller",
                  "check":true
               }
            ]
         },
         {
            "frage":"Zuerst sehen dann ...",
            "antworten":[
               {
                  "text":"treten",
                  "check":true
               },
               {
                  "text":"schlagen",
                  "check":false
               },
               {
                  "text":"liegen",
                  "check":false
               },
               {
                  "text":"essen",
                  "check":false
               }
            ]
         },
         {
            "frage":"Sag was",
            "antworten":[
               {
                  "text":"was?",
                  "check":false
               },
               {
                  "text":"was?!",
                  "check":false
               },
               {
                  "text":"was!",
                  "check":true
               },
               {
                  "text":"was!!",
                  "check":false
               }
            ]
         },
         {
            "frage":"Wer soll mal absteigen?",
            "antworten":[
               {
                  "text":"FC Bayern München",
                  "check":false
               },
               {
                  "text":"VfB Stuttgart",
                  "check":false
               },
               {
                  "text":"SV Werder Bremen",
                  "check":false
               },
               {
                  "text":"Hamburger SV",
                  "check":true
               }
            ]
         },
         {
            "frage":"Welcher Ball bringt den Sieg?",
            "antworten":[
               {
                  "text":"Der Fußball",
                  "check":false
               },
               {
                  "text":"Der Siegball",
                  "check":false
               },
               {
                  "text":"Der Tennisball",
                  "check":false
               },
               {
                  "text":"Die Seemine",
                  "check":true
               }
            ]
         },
         {
            "frage":"Wie viele Sechsecke hat ein Fußball?",
            "antworten":[
               {
                  "text":"vielleicht 20",
                  "check":false
               },
               {
                  "text":"vielleicht 18",
                  "check":false
               },
               {
                  "text":"vielleicht 16",
                  "check":true
               },
               {
                  "text":"vielleicht 12",
                  "check":false
               }
            ]
         },
         {
            "frage":"Wie nennt man einen Ball auch?",
            "antworten":[
               {
                  "text":"Ball",
                  "check":false
               },
               {
                  "text":"Fußball",
                  "check":true
               },
               {
                  "text":"B",
                  "check":false
               },
               {
                  "text":"Boing",
                  "check":false
               }
            ]
         },
         {
            "frage":"Wer wird das Quiz beim ersten spielen zu 100% richtig beantworten?",
            "antworten":[
               {
                  "text":"Gerd Müller",
                  "check":false
               },
               {
                  "text":"Thomas Müller",
                  "check":false
               },
               {
                  "text":"Pele",
                  "check":false
               },
               {
                  "text":"Wahrscheinlich keiner",
                  "check":true
               }
            ]
         },
         {
            "frage":"Wer hat sich dieses Quiz ausgedacht?",
            "antworten":[
               {
                  "text":"Ein Trottel",
                  "check":false
               },
               {
                  "text":"Ein Gorilla",
                  "check":false
               },
               {
                  "text":"Eine Giraffe",
                  "check":true
               },
               {
                  "text":"Bob",
                  "check":false
               }
            ]
         }
      ]
   },
   {
   "quizID":4,
   "quizFragen":[
      {
         "frage":"Wann wurde der 1. FC Köln gegründet?",
         "antworten":[
            {
               "text":"13. Februar 1948",
               "check":true
            },
            {
               "text":"12. Februar 1904",
               "check":false
            },
            {
               "text":"01. Juni 1924",
               "check":false
            },
            {
               "text":"11. November 1911",
               "check":false
            }
         ]
      },
      {
         "frage":"Wie ist der vollständige Name des 1. FC Kölns?",
         "antworten":[
            {
               "text":"1. Fußball-Club Köln 01/07 e. V.",
               "check":true
            },
            {
               "text":"1. Fußball Club Köln 01/07 GmbH",
               "check":false
            },
            {
               "text":"1. Fußball Club Colonia 01/07 e. V.",
               "check":false
            },
            {
               "text":"1. Football Club Cologne Inc.",
               "check":false
            }
         ]
      },
      {
         "frage":"Wie heißt der Geißbock, das Maskottchen, des 1. FC Köln?",
         "antworten":[
            {
               "text":"Hennes",
               "check":true
            },
            {
               "text":"Lukas",
               "check":false
            },
            {
               "text":"Henning",
               "check":false
            },
            {
               "text":"Major",
               "check":false
            }
         ]
      },
      {
         "frage":"In welchem Stadtteil von Köln ist das Rhein-Energie Stadion?",
         "antworten":[
            {
               "text":"Müngersdorf",
               "check":true
            },
            {
               "text":"Ehrenfeld",
               "check":false
            },
            {
               "text":"Hürth",
               "check":false
            },
            {
               "text":"Deutz",
               "check":false
            }
         ]
      },
      {
         "frage":"Wie oft wurde der 1. FC Köln deutscher Meister?",
         "antworten":[
            {
               "text":"Niemals",
               "check":false
            },
            {
               "text":"Viermal",
               "check":false
            },
            {
               "text":"Fünfmal",
               "check":false
            },
            {
               "text":"Dreimal",
               "check":true
            }
         ]
      },
      {
         "frage":"Welchen Platz belegte Köln bei der Saison 2015/16?",
         "antworten":[
            {
               "text":"9. Platz",
               "check":true
            },
            {
               "text":"12. Platz",
               "check":false
            },
            {
               "text":"7. Platz",
               "check":false
            },
            {
               "text":"15. Platz",
               "check":false
            }
         ]
      },
      {
         "frage":"Bei welchem Verein spielt Lukas Podolski derzeit?",
         "antworten":[
            {
               "text":"Galatasaray Istanbul",
               "check":true
            },
            {
               "text":"Fenerbahçe Istanbul",
               "check":false
            },
            {
               "text":"Beşiktaş Istanbul",
               "check":false
            },
            {
               "text":"1. FC Köln",
               "check":false
            }
         ]
      },
      {
         "frage":"Wieviele Zuschauer passen ins das Stadion des 1. FC Köln?",
         "antworten":[
            {
               "text":"c.a. 50.000",
               "check":true
            },
            {
               "text":"c.a. 70.000",
               "check":false
            },
            {
               "text":"c.a. 100.000",
               "check":false
            },
            {
               "text":"c.a. 32.000",
               "check":false
            }
         ]
      },
      {
         "frage":"Wer ist der aktuelle Hauptsponsor des 1. FC Köln?",
         "antworten":[
            {
               "text":"Rewe",
               "check":true
            },
            {
               "text":"Hit",
               "check":false
            },
            {
               "text":"Funny Frisch",
               "check":false
            },
            {
               "text":"Rhein Energie",
               "check":false
            }
         ]
      },
      {
         "frage":"Der 1. FC Köln hat neben seiner Männermannschaft auch eine Frauenfussballmannschaft. In welcher Liga spielen sie derzeit? (Saison 2016/2017)",
         "antworten":[
            {
               "text":"Regionalliga West",
               "check":true
            },
            {
               "text":"2. Bundesliga",
               "check":false
            },
            {
               "text":"Regionalliga Nord",
               "check":false
            },
            {
               "text":"1. Bundesliga",
               "check":false
            }
         ]
      },
      {
         "frage":"Wo ist die Heimat der 1. FC Köln Fans in ihrem Stadion?",
         "antworten":[
            {
               "text":"Südkurve",
               "check":true
            },
            {
               "text":"Nordkurve",
               "check":false
            },
            {
               "text":"Ostkurve",
               "check":false
            },
            {
               "text":"Westkurve",
               "check":false
            }
         ]
      },
      {
         "frage":"Wer ist der aktuelle Trainer des 1. FC Kölns? (Stand 11/2016)",
         "antworten":[
            {
               "text":"Peter Stöger",
               "check":true
            },
            {
               "text":"Rudi Völler",
               "check":false
            },
            {
               "text":"Holger Stanislawski",
               "check":false
            },
            {
               "text":"Ståle Solbakken",
               "check":false
            }
         ]
      },
      {
         "frage":"Die letzte Meisterschaft holte der FC 1978 vor Borussia Mönchengladbach. Wie wurde sie entschieden?",
         "antworten":[
            {
               "text":"Durch das bessere Torverhältniss",
               "check":true
            },
            {
               "text":"Durch ein Entscheidungsspiel",
               "check":false
            },
            {
               "text":"Durch einen klaren Punktvorsprung",
               "check":false
            },
            {
               "text":"Durch einen Münzwurf",
               "check":false
            }
         ]
      },
      {
         "frage":"Wie oft wurde der 1. FC Köln Vizemeister?",
         "antworten":[
            {
               "text":"Siebenmal",
               "check":true
            },
            {
               "text":"Zweimal",
               "check":false
            },
            {
               "text":"Fünfmal",
               "check":false
            },
            {
               "text":"Achtmal",
               "check":false
            }
         ]
      },
      {
         "frage":"In welchem Stadtteil Kölns wurde der FC in seiner heutigen Form gegründet?",
         "antworten":[
            {
               "text":"Sülz",
               "check":true
            },
            {
               "text":"Müngersdorf",
               "check":false
            },
            {
               "text":"Ehrenfeld",
               "check":false
            },
            {
               "text":"Südstadt",
               "check":false
            }
         ]
      },
      {
         "frage":"Welcher FC Trainer war bisher am längsten im Amt?",
         "antworten":[
            {
               "text":"Hennes Weisweiler",
               "check":true
            },
            {
               "text":"Rinus Michels",
               "check":false
            },
            {
               "text":"Hannes Löhr",
               "check":false
            },
            {
               "text":"Lukas Podolski",
               "check":false
            }
         ]
      },
      {
         "frage":"Gegen wen verlor der FC sein einziges Europapokalfinalspiel?",
         "antworten":[
            {
               "text":"Real Madrid",
               "check":true
            },
            {
               "text":"AC Mailand",
               "check":false
            },
            {
               "text":"FC Liverpool",
               "check":false
            },
            {
               "text":"FC Barcelona",
               "check":false
            }
         ]
      },
      {
         "frage":"Gegen welchen Gegner holte der FC die meisten Punkte der Bundesliga?",
         "antworten":[
            {
               "text":"VFB Stuttgart",
               "check":true
            },
            {
               "text":"Hamburger SV",
               "check":false
            },
            {
               "text":"Eintracht Frankfurt",
               "check":false
            },
            {
               "text":"Stürmer",
               "check":false
            }
         ]
      },
      {
         "frage":"Welches Wort kommt am häufigsten in der FC-Hymne vor?",
         "antworten":[
            {
               "text":"FC Kölle",
               "check":true
            },
            {
               "text":"Et",
               "check":false
            },
            {
               "text":"Schwöre",
               "check":false
            },
            {
               "text":"Alaaf",
               "check":false
            }
         ]
      },
      {
         "frage":"Welcher Spieler trägt den Titel Prinz?",
         "antworten":[
            {
               "text":"Lukas Podolski",
               "check":true
            },
            {
               "text":"Christopher Schorsch",
               "check":false
            },
            {
               "text":"Sebastian Freis",
               "check":false
            },
            {
               "text":"Christian Clemens",
               "check":false
            }
         ]
      },
      {
         "frage":"Wie wird der 1. FC Köln in der Öffentlichkeit noch dargestellt?",
         "antworten":[
            {
               "text":"als Karnevalsverein",
               "check":true
            },
            {
               "text":"als Retortenklub",
               "check":false
            },
            {
               "text":"als Traditionsverein",
               "check":false
            },
            {
               "text":"als Spaßverein",
               "check":false
            }
         ]
      },
      {
         "frage":"Wann war der FC zuletzt Deutscher Meister?",
         "antworten":[
            {
               "text":"1978",
               "check":true
            },
            {
               "text":"1962",
               "check":false
            },
            {
               "text":"1964",
               "check":false
            },
            {
               "text":"1983",
               "check":false
            }
         ]
      },
      {
         "frage":"Gegen wen gewann der FC 1983 den DFB-Pokal?",
         "antworten":[
            {
               "text":"Fortuna Köln",
               "check":true
            },
            {
               "text":"Hamburger SV",
               "check":false
            },
            {
               "text":"Werder Bremen",
               "check":false
            },
            {
               "text":"Bayern München",
               "check":false
            }
         ]
      },
      {
         "frage":"Wann ist der FC erstmals in die 2. Liga abgestiegen?",
         "antworten":[
            {
               "text":"1998",
               "check":true
            },
            {
               "text":"1997",
               "check":false
            },
            {
               "text":"1996",
               "check":false
            },
            {
               "text":"2000",
               "check":false
            }
         ]
      },
      {
         "frage":"Was war das Besondere, als der FC 1964 Deutscher Meister wurde?",
         "antworten":[
            {
               "text":"Es war die erste Bundesligasaison überhaupt",
               "check":true
            },
            {
               "text":"In der Saison spielten erstmals 20 Vereine in der Bundesliga",
               "check":false
            },
            {
               "text":"Der FC schlug Mönchengladbach mit 8:1",
               "check":false
            },
            {
               "text":"Es war der dritte Titel in Folge",
               "check":false
            }
         ]
      },
      {
         "frage":"Den wievielten Platz belegt der 1. FC Köln in der ewigen Tabelle der Bundesliga? (Stand 11/2016)",
         "antworten":[
            {
               "text":"Platz 8",
               "check":true
            },
            {
               "text":"Platz 14",
               "check":false
            },
            {
               "text":"Platz 5",
               "check":false
            },
            {
               "text":"Platz 14",
               "check":false
            }
         ]
      },
      {
         "frage":"Wer war Kölns erster Trainer?",
         "antworten":[
            {
               "text":"Karl Flink",
               "check":true
            },
            {
               "text":"Hennes Weisweiler",
               "check":false
            },
            {
               "text":"Helmut Schneider",
               "check":false
            },
            {
               "text":"Kappa",
               "check":false
            }
         ]
      },
      {
         "frage":"Wie viele Jahre spielte der 1. FC Köln in der 2. Bundesliga?",
         "antworten":[
            {
               "text":"8 Jahre",
               "check":true
            },
            {
               "text":"9 Jahre",
               "check":false
            },
            {
               "text":"12 Jahre",
               "check":false
            },
            {
               "text":"15 Jahre",
               "check":false
            }
         ]
      },
      {
         "frage":"Fünf Jahre nach Gründung des 1. FC Köln wurde 1953 ein Vereinsheim im Grüngürtel errichtet. Welchen Namen erhielt dieses?",
         "antworten":[
            {
               "text":"Geißbockheim",
               "check":true
            },
            {
               "text":"Geißbockhaus",
               "check":false
            },
            {
               "text":"Geißbocktreff",
               "check":false
            },
            {
               "text":"Geißböckchen",
               "check":false
            }
         ]
      },
      {
         "frage":"Welche Rückennummer trägt der FC Stammkeeper Timo Horn?",
         "antworten":[
            {
               "text":"1",
               "check":true
            },
            {
               "text":"3",
               "check":false
            },
            {
               "text":"5",
               "check":false
            },
            {
               "text":"8",
               "check":false
            }
         ]
      }
   ]
}
]
